pkbar/__init__.py
pkbar/pkbar.py
pkbar-0.5.dist-info/LICENSE
pkbar-0.5.dist-info/METADATA
pkbar-0.5.dist-info/WHEEL
pkbar-0.5.dist-info/top_level.txt
pkbar-0.5.dist-info/RECORD
